{
  "strategy": {
    "mode": "paper",
    "strategies": [
      {
        "name": "RSI_REVERSAL",
        "enabled": true,
        "priority": 10,
        "cooldown_sec": 300,
        "indicators": {
          "rsi": {
            "type": "rsi",
            "period": 7
          }
        },
        "entry_rule": {
          "logic": "AND",
          "conditions": [
            {
              "indicator": "rsi",
              "operator": "lt",
              "value": 20
            },
            {
              "indicator": "price",
              "operator": "gt",
              "value_ref": "prev_low"
            },
            {
              "indicator": "gap_pct",
              "operator": "gt",
              "value": -2.0
            },
            {
              "indicator": "hour",
              "operator": "lt",
              "value": 14
            },
            {
              "indicator": "kospi_pct",
              "operator": "gt",
              "value": -1.0
            },
            {
              "indicator": "prev_upper_wick_pct",
              "operator": "lt",
              "value": 3.0
            }
          ]
        },
        "exit_rule": {
          "logic": "OR",
          "conditions": [
            {
              "indicator": "rsi",
              "operator": "gt",
              "value": 80
            },
            {
              "indicator": "price",
              "operator": "gt",
              "value_ref": "prev_high"
            }
          ]
        }
      }
    ],
    "watchlist_strategies": {}
  }
}